README.md
setup.py
alertover/__init__.py
alertover/async.py
alertover/sync.py
alertover.egg-info/PKG-INFO
alertover.egg-info/SOURCES.txt
alertover.egg-info/dependency_links.txt
alertover.egg-info/requires.txt
alertover.egg-info/top_level.txt