Metadata-Version: 1.0
Name: alertover
Version: 1.0.1
Summary: Push message form your code to your devices with AlertOver. See: https://www.alertover.com/
Home-page: https://github.com/August-Ghost/alertover-python
Author: Ghost
Author-email: UNKNOWN
License: MIT
Keywords: AlertOver,pushing,message
Platform: UNKNOWN
